pmenv/__init__.py
pmenv/__version__.py
pmenv/datamanager.py
pmenv/environment.py
pmenv-1.0.1.dist-info/METADATA
pmenv-1.0.1.dist-info/WHEEL
pmenv-1.0.1.dist-info/top_level.txt
pmenv-1.0.1.dist-info/RECORD
