Metadata-Version: 2.1
Name: pmenv
Version: 1.0.1
Summary: A portfolio rebalancing task environment for reinforcement learning
Home-page: https://github.com/Yang-Hyun-Jun/pmenv.git
Author: hyunjun
Author-email: eppioes@gmail.com
License: MIT
Classifier: License :: OSI Approved :: MIT License
Classifier: Programming Language :: Python :: 3
Requires-Python: >=3.6
Requires-Dist: pandas
Requires-Dist: numpy
Requires-Dist: finance-datareader
